{
    "task": [
        {
            "name": "单线程工具-单本复刷",
            "label": "单本复刷",
            "entry": "单本复刷-任务开始层",
            "description": "除了连点器模式其他在战斗、编队、战中以外的界面都不会捣乱",
            "option": [
                "工具-单本复刷-刷取模式选择",
                // "工具-单本复刷-体力不足时动作"
            ]
        }
    ],
    "preset": [],
    "option": {
        "工具-单本复刷-刷取模式选择": {
            "type": "select",
            "label": "模式选择",
            "default_case": "工具-单本复刷-正常模式",
            "cases": [
                {
                    "name": "工具-单本复刷-正常模式",
                    "label": "正常模式",
                    "description": "编队处、战斗中、战斗结算界面启动后自动开始任务,其他地方启动后不会点击或超时",
                    "pipeline_override": {
                        "单本复刷-正常模式-引用层": {
                            "enabled": true
                        }
                    }
                },
                {
                    "name": "工具-单本复刷-连点器模式",
                    "label": "连点器模式",
                    "description": "战斗中、战斗结算界面启动,不识别纯点击,理论最快但不可控",
                    "pipeline_override": {
                        "单本复刷-连点器-引用层": {
                            "enabled": true
                        }
                    }
                },
                {
                    "name": "工具-单本复刷-生存战模式",
                    "label": "生存战模式",
                    "description": "手动战斗,每回合使用普攻快速过回合,其余和正常模式一样,需自行切换至手动战斗模式",
                    "pipeline_override": {
                        "单本复刷-生存战-引用层": {
                            "enabled": true
                        }
                    }
                }
            ]
        }
    }
}
